coragem/__init__.py
coragem/blockchain.py
coragem/cli.py
coragem-0.1.0.dist-info/licenses/LICENSE
tests/__init__.py
tests/test_cli.py
coragem-0.1.0.dist-info/METADATA
coragem-0.1.0.dist-info/WHEEL
coragem-0.1.0.dist-info/entry_points.txt
coragem-0.1.0.dist-info/top_level.txt
coragem-0.1.0.dist-info/RECORD
