Metadata-Version: 2.4
Name: coragem
Version: 0.1.0
Summary: Coragem: A CLI tool for querying blockchain data
Home-page: https://github.com/idyweb/coragem
Author: Idongesit Inyang
Author-email: inyangidongesit22@gmail.com
License: MIT
Project-URL: Source, https://github.com/idyweb/coragem
License-File: LICENSE
Requires-Dist: web3>=5.0.0
Requires-Dist: click>=8.0.0
Requires-Dist: requests>=2.0.0
Dynamic: author
Dynamic: author-email
Dynamic: description
Dynamic: description-content-type
Dynamic: home-page
Dynamic: license
Dynamic: license-file
Dynamic: project-url
Dynamic: requires-dist
Dynamic: summary
